configur8/__about__.py
configur8/__init__.py
configur8/cfg.py
configur8/core.py
configur8/email.py
configur8/env.py
configur8/path.py
configur8/py.typed
configur8/types.py
configur8/url.py
configur8/util.py
configur8-2.0.1.dist-info/WHEEL
configur8-2.0.1.dist-info/METADATA
configur8-2.0.1.dist-info/RECORD
