Metadata-Version: 2.1
Name: configur8
Version: 2.0.1
Summary: Type-safe configuration and validation library
License: MIT
Keywords: config,configuration,configurations,settings,env,environment,environments,application,python-config
Author-email: Nick Joyce <nick@stratuscode.com>
Requires-Python: >=3.7,<4.0
Classifier: Programming Language :: Python :: 3
Classifier: Programming Language :: Python :: 3.10
Classifier: Programming Language :: Python :: 3.11
Classifier: Programming Language :: Python :: 3.7
Classifier: Programming Language :: Python :: 3.8
Classifier: Programming Language :: Python :: 3.9
Classifier: Topic :: Software Development
Requires-Dist: email-validator>=1.3.1
Requires-Dist: typing-extensions>=4.0.0
